inmanta_plugins/terraform/__init__.py
inmanta_plugins/terraform/py.typed
inmanta_plugins/terraform/setup.cfg
inmanta_plugins/terraform/terraform_resource.py
inmanta_plugins/terraform/files/.gitkeep
inmanta_plugins/terraform/helpers/__init__.py
inmanta_plugins/terraform/helpers/attribute_reference.py
inmanta_plugins/terraform/helpers/const.py
inmanta_plugins/terraform/helpers/param_client.py
inmanta_plugins/terraform/helpers/utils.py
inmanta_plugins/terraform/model/_init.cf
inmanta_plugins/terraform/model/config.cf
inmanta_plugins/terraform/states/__init__.py
inmanta_plugins/terraform/states/generational_state_fact.py
inmanta_plugins/terraform/states/terraform_resource_state_fs.py
inmanta_plugins/terraform/states/terraform_resource_state_inmanta.py
inmanta_plugins/terraform/templates/.gitkeep
inmanta_plugins/terraform/tf/__init__.py
inmanta_plugins/terraform/tf/data.py
inmanta_plugins/terraform/tf/exceptions.py
inmanta_plugins/terraform/tf/terraform_provider.py
inmanta_plugins/terraform/tf/terraform_provider_installer.py
inmanta_plugins/terraform/tf/terraform_resource_client.py
inmanta_plugins/terraform/tf/terraform_resource_state.py
inmanta_module_terraform-1.3.14.dist-info/LICENSE
inmanta_module_terraform-1.3.14.dist-info/METADATA
inmanta_module_terraform-1.3.14.dist-info/WHEEL
inmanta_module_terraform-1.3.14.dist-info/top_level.txt
inmanta_module_terraform-1.3.14.dist-info/RECORD
