Metadata-Version: 2.1
Name: inmanta-module-terraform
Version: 1.3.14
License: ASL 2.0
License-File: LICENSE
Requires-Dist: inmanta-module-std
Requires-Dist: inmanta-tfplugin
Requires-Dist: msgpack
Requires-Dist: protobuf
Requires-Dist: grpcio !=1.49.0rc1,!=1.52.0rc1
